run_brer/__init__.py
run_brer/_version.py
run_brer/directory_helper.py
run_brer/metadata.py
run_brer/pair_data.py
run_brer/plugin_configs.py
run_brer/py.typed
run_brer/run_config.py
run_brer/run_data.py
run_brer/data/pair_data.json
run_brer/data/topol.tpr
run_brer-2.0.0b2.dist-info/LICENSE
run_brer-2.0.0b2.dist-info/METADATA
run_brer-2.0.0b2.dist-info/WHEEL
run_brer-2.0.0b2.dist-info/top_level.txt
run_brer-2.0.0b2.dist-info/zip-safe
run_brer-2.0.0b2.dist-info/RECORD
