Metadata-Version: 2.1
Name: run-brer
Version: 2.0.0b2
Summary: A set of scripts for running BRER simulations using gmxapi.
Author: Jennifer M. Hays, Kasson Lab BRER Team
Author-email: "Kasson Lab BRER Team" <kassonlab@gmail.com>
License: LGPL 2.1
Project-URL: Source, https://github.com/kassonlab/run_brer/
Project-URL: Documentation, https://kassonlab.github.io/run_brer/
Classifier: License :: OSI Approved :: GNU Lesser General Public License v2 or later (LGPLv2+)
Classifier: Programming Language :: Python :: 3
License-File: LICENSE
Requires-Dist: numpy (>=1)
